setup.py
pyside2_mess_server.egg-info/PKG-INFO
pyside2_mess_server.egg-info/SOURCES.txt
pyside2_mess_server.egg-info/dependency_links.txt
pyside2_mess_server.egg-info/requires.txt
pyside2_mess_server.egg-info/top_level.txt
server/__init__.py
server/__main__.py
server/server.py
server/common/__init__.py
server/common/arg_parser.py
server/common/decos.py
server/common/descriptors.py
server/common/host_ping.py
server/common/metaclasses.py
server/common/utils.py
server/jim/__init__.py
server/jim/core.py
server/jim/errors.py
server/log/__init__.py
server/log/client_log_config.py
server/log/server_log_config.py
server/server_db/__init__.py
server/server_db/server_data_services.py
server/server_db/data/__init__.py
server/server_db/data/session_factory.py
server/server_db/data/sqlalchemybase.py
server/server_db/db/__init__.py
server/server_db/db/db_folder.py
server/server_db/models/__init__.py
server/server_db/models/server_models.py
server/ui/__init__.py
server/ui/add_user.py
server/ui/connect_window_UIs.py
server/ui/modify_user.py
server/ui/remove_user.py
server/ui/server_gui.py
server/ui/style.py